btrsync/__init__.py
btrsync/cli.py
btrsync/cmdex.py
btrsync/util.py
btrsync/btrfs/__init__.py
btrsync/btrfs/cmd.py
btrsync/btrfs/parse.py
btrsync/sync/__init__.py
btrsync/sync/root/__init__.py
btrsync/sync/root/_exec.py
btrsync/sync/root/file.py
btrsync/sync/root/local.py
btrsync/sync/root/ssh.py
btrsync-0.3.dist-info/LICENSE
btrsync-0.3.dist-info/METADATA
btrsync-0.3.dist-info/WHEEL
btrsync-0.3.dist-info/entry_points.txt
btrsync-0.3.dist-info/top_level.txt
btrsync-0.3.dist-info/RECORD
